README.txt
setup.py
magentouch/__init__.py
magentouch/utils.py
magentouch.egg-info/PKG-INFO
magentouch.egg-info/SOURCES.txt
magentouch.egg-info/dependency_links.txt
magentouch.egg-info/requires.txt
magentouch.egg-info/top_level.txt