Metadata-Version: 1.0
Name: magentouch
Version: 1.0
Summary: Magento Soup v2 suds client
Home-page: https://github.com/jacobcui/magentouch
Author: Jacob CUI
Author-email: jacobcui123@gmail.com
License: GPL
Platform: UNKNOWN
